{"about_index.md":"ca5b59b1","about_me.md":"1cd64607","archives.md":"77fc9c7c","categories_fragments_2022_03_25_合并两个git仓库的历史提交记录.md":"6abd59e6","categories_fragments_2022_03_26_修改git最后一次提交记录的作者和邮箱.md":"d25ec020","categories_fragments_2022_03_27_修改git所有提交记录中的作者和邮箱.md":"cf48c3e5","categories_fragments_2022_03_28_为指定git仓库单独配置用户名和邮箱.md":"f22de45c","categories_fragments_index.md":"bf5af805","categories_issues_2021_12_01_f盘上的回收站已损坏。是否清空该驱动器上的回收站.md":"2bdf285b","categories_issues_2021_12_08_for循环中删除集合元素隐藏的陷阱.md":"5d112a47","categories_issues_2021_12_10_command line is too long. shorten command line for xxx or also for spring boot default configuration.md":"0510376d","categories_issues_2021_12_11_sql 注入攻击风险.md":"c04d3cf8","categories_issues_2021_12_13_无法访问f盘。文件或目录损坏且无法读取.md":"1964bf7d","categories_issues_2022_01_26_javascript 无法存储 java  long 类型数据问题.md":"0d01358a","categories_issues_2022_03_24_创建一个自身类的静态对象变量，究竟会如何执行？.md":"beb9cf76","categories_issues_2022_08_11_执行shell脚本，报java command not found.md":"d0457bb0","categories_issues_index.md":"5362e46c","categories_solutions_2021_11_18_用java8获取近n天日期.md":"b75926e6","categories_solutions_2021_11_22_一条sql查询今年每月统计信息.md":"02dff778","categories_solutions_index.md":"0693f35a","courses_mybatis_01-mybatis基础_01-快速入门.md":"8789dd8a","courses_mybatis_01-mybatis基础_02-核心对象.md":"41a900c5","courses_mybatis_01-mybatis基础_03-核心配置文件.md":"4485fe48","courses_mybatis_01-mybatis基础_04-sql映射文件之查询元素.md":"10dfc6c0","courses_mybatis_01-mybatis基础_05-sql映射文件之增删改元素.md":"97ba80d8","courses_mybatis_01-mybatis基础_06-sql映射文件之自定义映射元素.md":"84af87bf","courses_mybatis_01-mybatis基础_07-sql映射文件之缓存元素.md":"f5aa4b10","courses_mybatis_01-mybatis基础_08-动态sql.md":"6ae42351","courses_mybatis_index.md":"64d25d5f","index.md":"721fbdbe","tags.md":"ece8cffd"}
